auth_anywhere/__init__.py
auth_anywhere/middleware.py
django_auth_anywhere-0.0.2.dist-info/DESCRIPTION.rst
django_auth_anywhere-0.0.2.dist-info/METADATA
django_auth_anywhere-0.0.2.dist-info/RECORD
django_auth_anywhere-0.0.2.dist-info/WHEEL
django_auth_anywhere-0.0.2.dist-info/metadata.json
django_auth_anywhere-0.0.2.dist-info/top_level.txt
