Metadata-Version: 2.0
Name: django-auth-anywhere
Version: 0.0.2
Summary: django-auth-anywhere is a Django application which enables non-DRF views to authenticate using DRF backends.
Home-page: https://github.com/morgante/django-auth-anywhere
Author: Morgante Pell
Author-email: morgante.pell@morgante.net
License: MIT License
Keywords: django middleware rest framework api authentication jwt
Platform: any
Classifier: Development Status :: 5 - Production/Stable
Classifier: Environment :: Web Environment
Classifier: Framework :: Django
Classifier: Framework :: Django :: 1.8
Classifier: Framework :: Django :: 1.9
Classifier: Framework :: Django :: 1.10
Classifier: Intended Audience :: Developers
Classifier: License :: OSI Approved :: MIT License
Classifier: Operating System :: OS Independent
Classifier: Programming Language :: Python
Classifier: Programming Language :: Python :: 2
Classifier: Programming Language :: Python :: 2.7
Classifier: Programming Language :: Python :: 3
Classifier: Programming Language :: Python :: 3.5
Classifier: Topic :: Software Development :: Libraries :: Application Frameworks
Classifier: Topic :: Software Development :: Libraries :: Python Modules
